{"bpm":120,"chart_name":"Konga Conga Kappa (COTND)","song_path":"./Sound/Music/kingcongakappa.ogg","speed":1,"time_offset":0.07,"volume":-9,"wisps":[{"color":"black","lane":0,"time":0.875,"type":0},{"color":"black","lane":0,"time":1,"type":0},{"color":"black","lane":1,"time":1.5,"type":0},{"color":"black","lane":0,"time":1.875,"type":0},{"color":"black","lane":0,"time":2,"type":0},{"color":"black","lane":1,"time":2.5,"type":0},{"color":"black","lane":0,"time":2.875,"type":0},{"color":"black","lane":0,"time":3,"type":0},{"color":"white","lane":0,"time":3.625,"type":0},{"color":"white","lane":0,"time":3.875,"type":0},{"color":"white","lane":0,"time":4,"type":0},{"color":"black","lane":0,"time":4.125,"type":0},{"color":"black","lane":0,"time":4.5,"type":0},{"color":"black","lane":1,"time":4.875,"type":0},{"color":"black","lane":1,"time":5,"type":0},{"color":"black","lane":0,"time":5.5,"type":0},{"color":"black","lane":1,"time":5.875,"type":0},{"color":"black","lane":1,"time":6,"type":0},{"color":"black","lane":0,"time":6.5,"type":0},{"color":"black","lane":1,"time":6.875,"type":0},{"color":"black","lane":1,"time":7,"type":0},{"color":"white","lane":0,"length":0.35,"time":7.5,"type":1},{"color":"black","lane":0,"time":8,"type":0},{"color":"black","lane":1,"time":8.75,"type":0},{"color":"black","lane":1,"length":0.5,"time":9.125,"type":1},{"color":"black","lane":0,"time":10,"type":0},{"color":"black","lane":1,"time":10.637762,"type":0},{"color":"black","lane":1,"time":10.762762,"type":0},{"color":"black","lane":1,"length":0.125,"time":11,"type":1},{"color":"black","lane":0,"length":0.125,"time":11.5,"type":1},{"color":"black","lane":1,"time":12.25,"type":0},{"color":"black","lane":1,"time":12.625,"type":0},{"color":"black","lane":1,"time":12.6875,"type":0},{"color":"black","lane":0,"length":0.3,"time":13.3125,"type":1},{"color":"black","lane":0,"time":13.8125,"type":0},{"color":"black","lane":0,"time":13.875,"type":0},{"color":"black","lane":1,"length":0.525,"time":14.25,"type":1},{"color":"black","lane":0,"length":0.775,"time":15,"type":1},{"color":"black","lane":1,"length":0.5,"time":16,"type":1},{"color":"black","lane":0,"length":0.75,"time":17,"type":1},{"color":"black","lane":1,"length":0.725,"time":18,"type":1},{"color":"white","lane":0,"time":19.25,"type":0},{"color":"white","lane":0,"time":19.5,"type":0},{"color":"black","lane":0,"time":19.75,"type":0},{"color":"white","lane":1,"time":20,"type":0},{"color":"white","lane":1,"time":20.25,"type":0},{"color":"white","lane":1,"time":20.375,"type":0},{"color":"white","lane":1,"time":20.6875,"type":0},{"color":"white","lane":1,"time":20.875,"type":0},{"color":"white","lane":1,"time":21.125,"type":0},{"color":"white","lane":1,"time":21.375,"type":0},{"color":"white","lane":1,"time":21.6875,"type":0},{"color":"white","lane":1,"time":21.8125,"type":0},{"color":"white","lane":1,"time":21.9375,"type":0},{"color":"white","lane":1,"time":22.0625,"type":0},{"color":"white","lane":1,"time":22.3125,"type":0},{"color":"white","lane":1,"time":22.4375,"type":0},{"color":"white","lane":1,"time":22.6875,"type":0},{"color":"white","lane":1,"time":23,"type":0},{"color":"white","lane":0,"time":23.3125,"type":0},{"color":"white","lane":0,"time":23.5,"type":0},{"color":"white","lane":0,"time":23.6875,"type":0},{"color":"black","lane":0,"length":0.5,"time":24,"type":1},{"color":"black","lane":0,"length":0.9,"time":25,"type":1},{"color":"black","lane":1,"length":0.875,"time":26,"type":1},{"color":"black","lane":0,"length":0.75,"time":27,"type":1},{"color":"white","lane":1,"length":2.325,"time":28,"type":1},{"color":"black","lane":1,"length":0.675,"time":31,"type":1},{"color":"black","lane":0,"time":32,"type":0},{"color":"black","lane":1,"time":32.75,"type":0},{"color":"black","lane":1,"time":32.875,"type":0},{"color":"black","lane":1,"time":33,"type":0},{"color":"black","lane":0,"time":33.75,"type":0},{"color":"black","lane":0,"time":33.875,"type":0},{"color":"black","lane":0,"time":34,"type":0},{"color":"black","lane":1,"time":34.5,"type":0},{"color":"black","lane":0,"time":35,"type":0},{"color":"black","lane":0,"time":35.25,"type":0},{"color":"black","lane":0,"time":35.375,"type":0},{"color":"black","lane":0,"length":0.225,"time":35.75,"type":1},{"color":"black","lane":1,"length":0.6,"time":36.25,"type":1},{"color":"black","lane":0,"length":0.725,"time":37,"type":1},{"color":"black","lane":1,"length":0.775,"time":38,"type":1},{"color":"black","lane":0,"time":39.125,"type":0},{"color":"black","lane":0,"time":39.375,"type":0},{"color":"black","lane":0,"time":39.75,"type":0},{"color":"black","lane":0,"time":40,"type":0},{"color":"black","lane":0,"time":40.5,"type":0},{"color":"black","lane":1,"time":41,"type":0},{"color":"black","lane":1,"time":41.375,"type":0},{"color":"black","lane":1,"time":42,"type":0},{"color":"black","lane":1,"time":42.375,"type":0},{"color":"black","lane":1,"time":42.75,"type":0},{"color":"black","lane":1,"time":43,"type":0},{"color":"white","lane":0,"time":43.625,"type":0},{"color":"white","lane":0,"time":43.875,"type":0},{"color":"white","lane":0,"time":44,"type":0},{"color":"black","lane":0,"time":44.125,"type":0},{"color":"black","lane":0,"time":44.375,"type":0},{"color":"black","lane":1,"time":45,"type":0},{"color":"black","lane":1,"time":45.375,"type":0},{"color":"black","lane":1,"time":46,"type":0},{"color":"black","lane":1,"time":46.375,"type":0},{"color":"black","lane":1,"time":46.75,"type":0}],"highscore":247880}